django_exchange-0.7.1.dist-info/DESCRIPTION.rst
django_exchange-0.7.1.dist-info/METADATA
django_exchange-0.7.1.dist-info/pydist.json
django_exchange-0.7.1.dist-info/RECORD
django_exchange-0.7.1.dist-info/top_level.txt
django_exchange-0.7.1.dist-info/WHEEL
exchange/__init__.py
exchange/admin.py
exchange/cache.py
exchange/conversion.py
exchange/iso_4217.py
exchange/managers.py
exchange/models.py
exchange/tasks.py
exchange/tests.py
exchange/utils.py
exchange/adapters/__init__.py
exchange/adapters/openexchangerates.py
exchange/management/__init__.py
exchange/management/commands/__init__.py
exchange/management/commands/update_rates.py
exchange/migrations/0001_initial.py
exchange/migrations/0002_auto__chg_field_exchangerate_rate.py
exchange/migrations/__init__.py
