Metadata-Version: 2.0
Name: django-exchange
Version: 0.7.1
Summary: currency, exchange rates and conversions support for django
Home-page: https://github.com/metglobal/django-exchange
Author: Metglobal
Author-email: kadir.pekel@metglobal.com
License: MIT
Platform: UNKNOWN
Classifier: Development Status :: 5 - Production/Stable
Classifier: Intended Audience :: Developers
Classifier: Natural Language :: English
Classifier: License :: OSI Approved :: MIT License
Classifier: Operating System :: OS Independent
Classifier: Programming Language :: Python
Classifier: Programming Language :: Python :: 2.7
Classifier: Topic :: Internet :: WWW/HTTP
Requires-Dist: openexchangerates
